Workbook

Sheet Dmart_RetailBusiness
A1: order_id | B1: region | C1: category | D1: sales | E1: discount | F1: quantity | G1: order_date | H1: delivery_date | I1: customer_type | J1: payment_mode | K1: profit | L1: city
A2: ORD100000 | B2: East | C2: Clothing | D2: 713.49 | E2: 0.31 | F2: 3 | G2: 45015 | H2: 45017 | I2: Member | J2: UPI | K2: 114.72 | L2: Pune
A3: ORD100001 | B3: West | C3: Electronics | D3: 3802.97 | E3: 0.38 | F3: 4 | G3: 45166 | H3: 45172 | I3: Regular | J3: Card | K3: 971.41 | L3: Hyderabad
A4: ORD100002 | B4: North | C4: Home Care | D4: 3588.97 | E4: 0.1 | F4: 7 | G4: 45360 | H4: 45366 | I4: Regular | J4: Cash | K4: 769.08 | L4: Bangalore
A5: ORD100003 | B5: East | C5: Electronics | D5: 1160.86 | E5: 0.27 | F5: 5 | G5: 45578 | H5: 45584 | I5: Member | J5: UPI | K5: 71.61 | L5: Pune
A6: ORD100004 | B6: East | C6: Electronics | D6: 3071.32 | E6: 0 | F6: 7 | G6: 45022 | H6: 45025 | I6: New | J6: Cash | K6: 621.92 | L6: Bangalore
A7: ORD100005 | B7: West | C7: Grocery | D7: 2566.18 | E7: 0.02 | F7: 6 | G7: 45108 | H7: 45111 | I7: Member | J7: UPI | K7: 578.94 | L7: Mumbai
A8: ORD100006 | B8: North | C8: Personal Care | D8: 398 | E8: 0.16 | F8: 4 | G8: 45119 | H8: 45124 | I8: New | J8: Cash | K8: 110.31 | L8: Mumbai
A9: ORD100007 | B9: North | C9: Personal Care | D9: 1462.95 | E9: 0.23 | F9: 2 | G9: 45064 | H9: 45066 | I9: Regular | J9: UPI | K9: 91.68 | L9: Bangalore
A10: ORD100008 | B10: East | C10: Personal Care | D10: 4997.47 | E10: 0.29 | F10: 6 | G10: 45296 | H10: 45299 | I10: Regular | J10: Card | K10: 995.78 | L10: Delhi
A11: ORD100009 | B11: South | C11: Grocery | D11: 587.72 | E11: 0.44 | F11: 6 | G11: 45514 | H11: 45521 | I11: New | J11: Cash | K11: 102.96 | L11: Pune
A12: ORD100010 | B12: East | C12: Clothing | D12: 2581.42 | E12: 0.39 | F12: 6 | G12: 45419 | H12: 45420 | I12: Regular | J12: Cash | K12: 542.82 | L12: Bangalore
A13: ORD100011 | B13: East | C13: Clothing | D13: 4261.74 | E13: 0.15 | F13: 1 | G13: 45171 | H13: 45172 | I13: New | J13: UPI | K13: 1028.47 | L13: Pune
... A15346: ORD115344 | B15346: South | C15346: Grocery | D15346: 4984.32 | E15346: 0.21 | F15346: 3 | G15346: 45248 | H15346: 45249 | I15346: New | J15346: Card | K15346: 909.1 | L15346: Bangalore

Sheet lab 8
A1: order_id | B1: sales | C1: profit | D1: city
A2: ORD100000 | B2: =VLOOKUP(A2,Dmart_RetailBusiness!$A$1:$L$15346,4,0) -> 713.49 | C2: xlookup | D2: =INDEX(Dmart_RetailBusiness!$A$1:$L$15346,MATCH('lab 8'!$A2,Dmart_RetailBusiness!$A$1:$A$15346,0),12) -> Pune
A3: ORD100001 | B3: =VLOOKUP(A3,Dmart_RetailBusiness!$A$1:$L$15346,4,0) -> 3802.97 | D3: =INDEX(Dmart_RetailBusiness!$A$1:$L$15346,MATCH('lab 8'!$A3,Dmart_RetailBusiness!$A$1:$A$15346,0),12) -> Hyderabad
A4: ORD100002 | B4: =VLOOKUP(A4,Dmart_RetailBusiness!$A$1:$L$15346,4,0) -> 3588.97 | D4: =INDEX(Dmart_RetailBusiness!$A$1:$L$15346,MATCH('lab 8'!$A4,Dmart_RetailBusiness!$A$1:$A$15346,0),12) -> Bangalore
A5: ORD100003 | B5: =VLOOKUP(A5,Dmart_RetailBusiness!$A$1:$L$15346,4,0) -> 1160.86 | D5: =INDEX(Dmart_RetailBusiness!$A$1:$L$15346,MATCH('lab 8'!$A5,Dmart_RetailBusiness!$A$1:$A$15346,0),12) -> Pune
A6: ORD100004 | B6: =VLOOKUP(A6,Dmart_RetailBusiness!$A$1:$L$15346,4,0) -> 3071.32 | D6: =INDEX(Dmart_RetailBusiness!$A$1:$L$15346,MATCH('lab 8'!$A6,Dmart_RetailBusiness!$A$1:$A$15346,0),12) -> Bangalore
A7: ORD100005 | B7: =VLOOKUP(A7,Dmart_RetailBusiness!$A$1:$L$15346,4,0) -> 2566.18 | D7: =INDEX(Dmart_RetailBusiness!$A$1:$L$15346,MATCH('lab 8'!$A7,Dmart_RetailBusiness!$A$1:$A$15346,0),12) -> Mumbai
A8: ORD100006 | B8: =VLOOKUP(A8,Dmart_RetailBusiness!$A$1:$L$15346,4,0) -> 398 | D8: =INDEX(Dmart_RetailBusiness!$A$1:$L$15346,MATCH('lab 8'!$A8,Dmart_RetailBusiness!$A$1:$A$15346,0),12) -> Mumbai
A9: ORD100007 | B9: =VLOOKUP(A9,Dmart_RetailBusiness!$A$1:$L$15346,4,0) -> 1462.95 | D9: =INDEX(Dmart_RetailBusiness!$A$1:$L$15346,MATCH('lab 8'!$A9,Dmart_RetailBusiness!$A$1:$A$15346,0),12) -> Bangalore
A10: ORD100008 | B10: =VLOOKUP(A10,Dmart_RetailBusiness!$A$1:$L$15346,4,0) -> 4997.47 | D10: =INDEX(Dmart_RetailBusiness!$A$1:$L$15346,MATCH('lab 8'!$A10,Dmart_RetailBusiness!$A$1:$A$15346,0),12) -> Delhi
A11: ORD100009 | B11: =VLOOKUP(A11,Dmart_RetailBusiness!$A$1:$L$15346,4,0) -> 587.72 | D11: =INDEX(Dmart_RetailBusiness!$A$1:$L$15346,MATCH('lab 8'!$A11,Dmart_RetailBusiness!$A$1:$A$15346,0),12) -> Pune
A12: ORD100010 | B12: =VLOOKUP(A12,Dmart_RetailBusiness!$A$1:$L$15346,4,0) -> 2581.42 | D12: =INDEX(Dmart_RetailBusiness!$A$1:$L$15346,MATCH('lab 8'!$A12,Dmart_RetailBusiness!$A$1:$A$15346,0),12) -> Bangalore
A13: ORD100011 | B13: =VLOOKUP(A13,Dmart_RetailBusiness!$A$1:$L$15346,4,0) -> 4261.74 | D13: =INDEX(Dmart_RetailBusiness!$A$1:$L$15346,MATCH('lab 8'!$A13,Dmart_RetailBusiness!$A$1:$A$15346,0),12) -> Pune
A14: ORD100012 | B14: =VLOOKUP(A14,Dmart_RetailBusiness!$A$1:$L$15346,4,0) -> 1573.19 | D14: =INDEX(Dmart_RetailBusiness!$A$1:$L$15346,MATCH('lab 8'!$A14,Dmart_RetailBusiness!$A$1:$A$15346,0),12) -> Bangalore
... A15346: ORD115344 | B15346: =VLOOKUP(A15346,Dmart_RetailBusiness!$A$1:$L$15346,4,0) -> 4984.32 | D15346: =INDEX(Dmart_RetailBusiness!$A$1:$L$15346,MATCH('lab 8'!$A15346,Dmart_RetailBusiness!$A$1:$A$15346,0),12) -> Bangalore
